releasio/__init__.py
releasio/__main__.py
releasio/exceptions.py
releasio/py.typed
releasio/cli/__init__.py
releasio/cli/app.py
releasio/cli/commands/__init__.py
releasio/cli/commands/check.py
releasio/cli/commands/check_pr.py
releasio/cli/commands/do_release.py
releasio/cli/commands/init_cmd.py
releasio/cli/commands/release.py
releasio/cli/commands/release_pr.py
releasio/cli/commands/update.py
releasio/config/__init__.py
releasio/config/loader.py
releasio/config/models.py
releasio/core/__init__.py
releasio/core/changelog.py
releasio/core/commits.py
releasio/core/security.py
releasio/core/version.py
releasio/forge/__init__.py
releasio/forge/base.py
releasio/forge/github.py
releasio/forge/gitlab.py
releasio/project/__init__.py
releasio/project/detector.py
releasio/project/lockfile.py
releasio/project/pyproject.py
releasio/project/workspace.py
releasio/publish/__init__.py
releasio/publish/pypi.py
releasio/vcs/__init__.py
releasio/vcs/git.py
releasio-2.4.1.dist-info/METADATA
releasio-2.4.1.dist-info/WHEEL
releasio-2.4.1.dist-info/entry_points.txt
releasio-2.4.1.dist-info/licenses/LICENSE
releasio-2.4.1.dist-info/RECORD
