Metadata-Version: 2.4
Name: releasio
Version: 2.4.1
Summary: Best-in-class Python release automation, inspired by release-plz
Project-URL: Homepage, https://github.com/mikeleppane/release-py
Project-URL: Documentation, https://mikeleppane.github.io/releasio/
Project-URL: Repository, https://github.com/mikeleppane/release-py
Project-URL: Issues, https://github.com/mikeleppane/release-py/issues
Author-email: Mikko <mikko@example.com>
License-Expression: MIT
License-File: LICENSE
Keywords: automation,changelog,git-cliff,release,versioning
Classifier: Development Status :: 3 - Alpha
Classifier: Environment :: Console
Classifier: Intended Audience :: Developers
Classifier: License :: OSI Approved :: MIT License
Classifier: Operating System :: OS Independent
Classifier: Programming Language :: Python :: 3
Classifier: Programming Language :: Python :: 3.11
Classifier: Programming Language :: Python :: 3.12
Classifier: Programming Language :: Python :: 3.13
Classifier: Topic :: Software Development :: Build Tools
Classifier: Topic :: Software Development :: Version Control :: Git
Classifier: Typing :: Typed
Requires-Python: >=3.11
Requires-Dist: httpx>=0.28.0
Requires-Dist: pydantic-settings>=2.0.0
Requires-Dist: pydantic>=2.0.0
Requires-Dist: rich>=13.0.0
Requires-Dist: typer>=0.21.0
Provides-Extra: dev
Requires-Dist: hypothesis>=6.100.0; extra == 'dev'
Requires-Dist: mypy>=1.18.1; extra == 'dev'
Requires-Dist: pre-commit>=4.0.0; extra == 'dev'
Requires-Dist: pytest-asyncio>=0.25.0; extra == 'dev'
Requires-Dist: pytest-cov>=6.0.0; extra == 'dev'
Requires-Dist: pytest-mock>=3.14.0; extra == 'dev'
Requires-Dist: pytest>=8.0.0; extra == 'dev'
Requires-Dist: ruff>=0.14.10; extra == 'dev'
Provides-Extra: docs
Requires-Dist: mkdocs-gen-files>=0.5.0; extra == 'docs'
Requires-Dist: mkdocs-git-revision-date-localized-plugin>=1.2.0; extra == 'docs'
Requires-Dist: mkdocs-literate-nav>=0.6.0; extra == 'docs'
Requires-Dist: mkdocs-material>=9.5.0; extra == 'docs'
Requires-Dist: mkdocs-section-index>=0.3.0; extra == 'docs'
Requires-Dist: mkdocs>=1.6.0; extra == 'docs'
Requires-Dist: mkdocstrings[python]>=0.26.0; extra == 'docs'
Requires-Dist: pymdown-extensions>=10.0; extra == 'docs'
